docking/__init__.py
docking/np_docking.py
docking/vina_dock.py
docking/vina_helper.py
mutation/Amino.py
mutation/__init__.py
mutation/csv_generator.py
mutation/csv_sort.py
mutation/ddg_calc.py
mutation/ddg_calc_double.py
mutation/ddg_calc_triple.py
mutation/generate_mutants.py
mutation/helpers.py
mutation/install_dependencies.py
mutation/np_mutation.py
mutation/predict_ddG.py
mutadock-1.9.3.dist-info/METADATA
mutadock-1.9.3.dist-info/WHEEL
mutadock-1.9.3.dist-info/entry_points.txt
mutadock-1.9.3.dist-info/licenses/LICENSE
mutadock-1.9.3.dist-info/RECORD
