Metadata-Version: 2.3
Name: mutadock
Version: 1.9.3
Summary: MUTADOCK is a comprehensive library designed for mutation studies and multiple receptor-ligand docking. Refer to README for more information.
Project-URL: Repository, https://github.com/naisarg14/mutadock
Project-URL: Issues, https://github.com/naisarg14/mutadock/issues
Project-URL: Documentation, https://mutadock.readthedocs.io/en/latest/
Author-email: Naisarg Patel <naisarg.patel14@hotmail.com>
License: GPL-3.0
License-File: LICENSE
Keywords: Bioinformatics,Biology,Docking,Mutation
Classifier: Development Status :: 4 - Beta
Classifier: Intended Audience :: Education
Classifier: License :: OSI Approved :: GNU General Public License v3 (GPLv3)
Classifier: Programming Language :: Python :: 3
Classifier: Programming Language :: Python :: 3.6
Classifier: Programming Language :: Python :: 3.7
Classifier: Programming Language :: Python :: 3.8
Classifier: Programming Language :: Python :: 3.9
Classifier: Programming Language :: Python :: 3.10
Classifier: Programming Language :: Python :: 3.11
Classifier: Programming Language :: Python :: 3.12
Classifier: Topic :: Scientific/Engineering :: Bio-Informatics
Requires-Dist: biopython==1.84
Requires-Dist: meeko==0.5.0
Requires-Dist: numpy>=2.1.1
Requires-Dist: pandas==2.2.2
Requires-Dist: pyarrow==17.0.0
Requires-Dist: pyrosetta-installer==0.1.1
Requires-Dist: tqdm>=4.66.5
